mlpforecast/.DS_Store
mlpforecast/__init__.py
mlpforecast/data/__init__.py
mlpforecast/data/loader.py
mlpforecast/data/processing.py
mlpforecast/data/transform.py
mlpforecast/evaluation/__init__.py
mlpforecast/evaluation/backtester.py
mlpforecast/forecaster/__init__.py
mlpforecast/forecaster/common.py
mlpforecast/forecaster/mlp.py
mlpforecast/forecaster/utils.py
mlpforecast/metrics/__init__.py
mlpforecast/metrics/deterministic.py
mlpforecast/metrics/probabilistic.py
mlpforecast/model/__init__.py
mlpforecast/model/base_model.py
mlpforecast/model/deterministic.py
mlpforecast/net/__init__.py
mlpforecast/net/embending.py
mlpforecast/net/layers.py
mlpforecast/plot/__init__.py
mlpforecast/plot/visual_functions.py
mlpforecast/stats/__init__.py
mlpforecast/stats/corr.py
mlpforecast-0.1.2.dist-info/LICENSE
mlpforecast-0.1.2.dist-info/METADATA
mlpforecast-0.1.2.dist-info/WHEEL
mlpforecast-0.1.2.dist-info/RECORD
