Metadata-Version: 2.1
Name: mlpforecast
Version: 0.1.2
Summary: Multilayer Perceptron Learning Models for Time Series Forecasting
Author: sambaiga
Author-email: sambaiga@gmail.com
Requires-Python: >=3.11,<3.12
Classifier: Programming Language :: Python :: 3
Classifier: Programming Language :: Python :: 3.11
Requires-Dist: altair (>=5.3.0)
Requires-Dist: arviz (>=0.18.0,<0.19.0)
Requires-Dist: astral (>=3.2,<4.0)
Requires-Dist: coreforecast (>=0.0.6,<0.0.7)
Requires-Dist: lightning (>=2.0.8,<3.0.0)
Requires-Dist: matplotlib (>=3.8.4,<4.0.0)
Requires-Dist: matplotlib_inline (>=0.1.6)
Requires-Dist: numpy (>=1.24.3,<2.0.0)
Requires-Dist: optuna (>=3.2.0,<4.0.0)
Requires-Dist: optuna-integration (>=3.6.0,<4.0.0)
Requires-Dist: pandas (==1.5.3)
Requires-Dist: pmdarima (>=2.0.4,<3.0.0)
Requires-Dist: ppscore (>=1.3.0,<2.0.0)
Requires-Dist: pyarrow (>=13.0.0,<14.0.0)
Requires-Dist: pytimetk (>=0.4.0,<0.5.0)
Requires-Dist: rich (>=13.7.1,<14.0.0)
Requires-Dist: scikit-learn (==1.5.1)
Requires-Dist: seaborn (>=0.13.2)
Requires-Dist: statsmodels (>=0.14.0)
Requires-Dist: tensorboard (>=2.1.5,<3.0.0)
Requires-Dist: torch (>=2.0.1,<3.0.0)
Requires-Dist: torchmetrics (>=1.4.0,<2.0.0)
Requires-Dist: tqdm (>=4.66.4,<5.0.0)
Requires-Dist: utilsforecast (>=0.0.25,<0.0.26)
Requires-Dist: vl-convert-python (>1.4.0)
Requires-Dist: wandb (>=0.17.4,<0.18.0)
